seqmatcher/__init__.py
seqmatcher-0.1.0.dist-info/LICENSE
seqmatcher-0.1.0.dist-info/METADATA
seqmatcher-0.1.0.dist-info/WHEEL
seqmatcher-0.1.0.dist-info/top_level.txt
seqmatcher-0.1.0.dist-info/RECORD
