Metadata-Version: 2.1
Name: seqmatcher
Version: 0.1.0
Summary: match and edit sequences of events
Home-page: https://github.com/ananis25/seqmatcher
Author: Ishan Anand
License: UNKNOWN
Platform: UNKNOWN
Classifier: Programming Language :: Python :: 3 :: Only
Classifier: License :: OSI Approved :: MIT License
Classifier: Operating System :: OS Independent
Requires-Python: >=3.7
License-File: LICENSE
Requires-Dist: parsy (>=1.4)
Provides-Extra: test
Requires-Dist: pytest (>=7.0) ; extra == 'test'
